<annotation>
	<folder>wetransfer-3b2519</folder>
	<filename>IMG_4808.JPG</filename>
	<path>C:\Users\colo_\Desktop\proyecto-lifia_\Imagenes\Oidio\wetransfer-3b2519\IMG_4808.JPG</path>
	<source>
		<database>Unknown</database>
	</source>
	<size>
		<width>3264</width>
		<height>2448</height>
		<depth>3</depth>
	</size>
	<segmented>0</segmented>
	<object>
		<name>blanca</name>
		<pose>Unspecified</pose>
		<truncated>0</truncated>
		<difficult>0</difficult>
		<bndbox>
			<xmin>834</xmin>
			<ymin>794</ymin>
			<xmax>1067</xmax>
			<ymax>991</ymax>
		</bndbox>
	</object>
	<object>
		<name>blanca</name>
		<pose>Unspecified</pose>
		<truncated>0</truncated>
		<difficult>0</difficult>
		<bndbox>
			<xmin>1126</xmin>
			<ymin>1224</ymin>
			<xmax>1811</xmax>
			<ymax>1617</ymax>
		</bndbox>
	</object>
	<object>
		<name>blanca</name>
		<pose>Unspecified</pose>
		<truncated>0</truncated>
		<difficult>0</difficult>
		<bndbox>
			<xmin>2297</xmin>
			<ymin>1420</ymin>
			<xmax>2782</xmax>
			<ymax>1883</ymax>
		</bndbox>
	</object>
	<object>
		<name>blanca</name>
		<pose>Unspecified</pose>
		<truncated>1</truncated>
		<difficult>0</difficult>
		<bndbox>
			<xmin>3111</xmin>
			<ymin>539</ymin>
			<xmax>3264</xmax>
			<ymax>785</ymax>
		</bndbox>
	</object>
	<object>
		<name>blanca</name>
		<pose>Unspecified</pose>
		<truncated>0</truncated>
		<difficult>0</difficult>
		<bndbox>
			<xmin>1315</xmin>
			<ymin>357</ymin>
			<xmax>1608</xmax>
			<ymax>724</ymax>
		</bndbox>
	</object>
	<object>
		<name>blanca</name>
		<pose>Unspecified</pose>
		<truncated>1</truncated>
		<difficult>0</difficult>
		<bndbox>
			<xmin>2226</xmin>
			<ymin>2320</ymin>
			<xmax>2534</xmax>
			<ymax>2448</ymax>
		</bndbox>
	</object>
</annotation>
