<annotation>
	<folder>wetransfer-3b2519</folder>
	<filename>IMG_5901.JPG</filename>
	<path>C:\Users\colo_\Desktop\proyecto-lifia_\Imagenes\Oidio\wetransfer-3b2519\IMG_5901.JPG</path>
	<source>
		<database>Unknown</database>
	</source>
	<size>
		<width>3264</width>
		<height>2448</height>
		<depth>3</depth>
	</size>
	<segmented>0</segmented>
	<object>
		<name>blanca</name>
		<pose>Unspecified</pose>
		<truncated>0</truncated>
		<difficult>0</difficult>
		<bndbox>
			<xmin>619</xmin>
			<ymin>1183</ymin>
			<xmax>923</xmax>
			<ymax>1594</ymax>
		</bndbox>
	</object>
	<object>
		<name>blanca</name>
		<pose>Unspecified</pose>
		<truncated>0</truncated>
		<difficult>0</difficult>
		<bndbox>
			<xmin>1160</xmin>
			<ymin>1009</ymin>
			<xmax>1930</xmax>
			<ymax>1739</ymax>
		</bndbox>
	</object>
	<object>
		<name>blanca</name>
		<pose>Unspecified</pose>
		<truncated>0</truncated>
		<difficult>0</difficult>
		<bndbox>
			<xmin>2019</xmin>
			<ymin>976</ymin>
			<xmax>2263</xmax>
			<ymax>1194</ymax>
		</bndbox>
	</object>
	<object>
		<name>blanca</name>
		<pose>Unspecified</pose>
		<truncated>0</truncated>
		<difficult>0</difficult>
		<bndbox>
			<xmin>2363</xmin>
			<ymin>842</ymin>
			<xmax>2619</xmax>
			<ymax>994</ymax>
		</bndbox>
	</object>
	<object>
		<name>blanca</name>
		<pose>Unspecified</pose>
		<truncated>0</truncated>
		<difficult>0</difficult>
		<bndbox>
			<xmin>2341</xmin>
			<ymin>1139</ymin>
			<xmax>2704</xmax>
			<ymax>1402</ymax>
		</bndbox>
	</object>
	<object>
		<name>blanca</name>
		<pose>Unspecified</pose>
		<truncated>0</truncated>
		<difficult>0</difficult>
		<bndbox>
			<xmin>2260</xmin>
			<ymin>1691</ymin>
			<xmax>2363</xmax>
			<ymax>1791</ymax>
		</bndbox>
	</object>
	<object>
		<name>blanca</name>
		<pose>Unspecified</pose>
		<truncated>0</truncated>
		<difficult>0</difficult>
		<bndbox>
			<xmin>2000</xmin>
			<ymin>1324</ymin>
			<xmax>2123</xmax>
			<ymax>1446</ymax>
		</bndbox>
	</object>
	<object>
		<name>blanca</name>
		<pose>Unspecified</pose>
		<truncated>0</truncated>
		<difficult>0</difficult>
		<bndbox>
			<xmin>2200</xmin>
			<ymin>1350</ymin>
			<xmax>2282</xmax>
			<ymax>1420</ymax>
		</bndbox>
	</object>
	<object>
		<name>blanca</name>
		<pose>Unspecified</pose>
		<truncated>0</truncated>
		<difficult>0</difficult>
		<bndbox>
			<xmin>1604</xmin>
			<ymin>1779</ymin>
			<xmax>1860</xmax>
			<ymax>1965</ymax>
		</bndbox>
	</object>
	<object>
		<name>blanca</name>
		<pose>Unspecified</pose>
		<truncated>0</truncated>
		<difficult>0</difficult>
		<bndbox>
			<xmin>1826</xmin>
			<ymin>724</ymin>
			<xmax>1948</xmax>
			<ymax>854</ymax>
		</bndbox>
	</object>
	<object>
		<name>blanca</name>
		<pose>Unspecified</pose>
		<truncated>0</truncated>
		<difficult>0</difficult>
		<bndbox>
			<xmin>1574</xmin>
			<ymin>717</ymin>
			<xmax>1708</xmax>
			<ymax>831</ymax>
		</bndbox>
	</object>
</annotation>
